ujq/__init__.py
ujq/redis_lib.py
ujq-2.0.dist-info/LICENSE
ujq-2.0.dist-info/METADATA
ujq-2.0.dist-info/WHEEL
ujq-2.0.dist-info/top_level.txt
ujq-2.0.dist-info/RECORD
