Metadata-Version: 2.1
Name: ujq
Version: 2.0
Summary: Universal Job Queue or UJQ in short is a Redis based Simple MultiPlatform Job management library build. This Library is light weight and build for working with microservices.
Home-page: https://github.com/Krishnaraj2003/PyUJQ
Author: Krishna Raj K
Author-email: krishnaraj2003@gmail.com
License: MIT
Download-URL: https://github.com/Krishnaraj2003/PyUJQ/archive/v2.0.0.tar.gz
Keywords: UJQ,Redis,ujq,micro services,microservice,redis queue,queue management
Platform: UNKNOWN
Classifier: Development Status :: 5 - Production/Stable
Classifier: Intended Audience :: Developers
Classifier: Topic :: Software Development :: Build Tools
Classifier: License :: OSI Approved :: MIT License
Classifier: Programming Language :: Python :: 3
Classifier: Programming Language :: Python :: 3.6
Classifier: Programming Language :: Python :: 3.7
Classifier: Programming Language :: Python :: 3.8
Requires-Dist: redis
